turbopod/__init__.py
turbopod/authpage.html
turbopod/cache.py
turbopod/cli.py
turbopod/dataframe.py
turbopod/helpers.py
turbopod/items.py
turbopod/podio_auth.py
turbopod/session.py
turbopod-0.0.2.dist-info/METADATA
turbopod-0.0.2.dist-info/WHEEL
turbopod-0.0.2.dist-info/licenses/LICENSE
turbopod-0.0.2.dist-info/RECORD
