Metadata-Version: 2.4
Name: turbopod
Version: 0.0.2
Summary: A modern utility package for using the Podio API with Python.
Project-URL: Homepage, https://github.com/uwekamper/turbopod
Project-URL: Issues, https://github.com/uwekamper/turbopod/issues
Author-email: Uwe Kamper <me@uwekamper.de>
License-File: LICENSE
Classifier: License :: OSI Approved :: MIT License
Classifier: Operating System :: OS Independent
Classifier: Programming Language :: Python :: 3
Requires-Python: >=3.8
Requires-Dist: click
Requires-Dist: python-dateutil
Requires-Dist: requests
Requires-Dist: requests-oauthlib
